{
    "id": 11223,
    "map_id": 13,
    "name": "Gooseberry",
    "date": "2024-08-30T09:10:11.000Z",
    "author": "nextir",
    "author_id": 2994,
    "last_updated": "2024-08-31T07:42:17.000Z",
    "last_updated_author_id": 2994,
    "active": 1,
    "ranked": 1,
    "tier": 4,
    "points": 1000,
    "max_prestrafe": 300,
    "completions": "0",
    "players_completed": "0",
    "average_rating": "0.0000",
    "sequence": [
        {
            "trigger_id": 3445,
            "name": "T2 Boost Platform",
            "order": 0,
            "passthrough": 0
        },
        {
            "trigger_id": 3444,
            "name": "T2 Boost",
            "order": 1,
            "passthrough": 0
        },
        {
            "trigger_id": 3455,
            "name": "T2 Wing",
            "order": 2,
            "passthrough": 0
        },
        {
            "trigger_id": 3346,
            "name": "Main Ramp",
            "order": 3,
            "passthrough": 0
        },
        {
            "trigger_id": 3500,
            "name": "Tower Platform",
            "order": 4,
            "passthrough": 0
        }
    ]
}