{"id":12278,"map_id":13,"name":"john porg on crack","date":"2025-02-27T12:58:47.000Z","author":"john porg wr holder","author_id":18519,"last_updated":null,"last_updated_author_id":null,"active":1,"ranked":1,"tier":7,"subtier":1,"max_prestrafe":406,"completions":"0","players_completed":"0","average_rating":"0.0000","sequence":[{"trigger_id":3364,"name":"North Elevator Window Ground","order":0,"passthrough":0},{"trigger_id":3305,"name":"Elevator","order":1,"passthrough":0},{"trigger_id":3507,"name":"Turtle Acid Ramp","order":2,"passthrough":0},{"trigger_id":3327,"name":"Jumper","order":3,"passthrough":0},{"trigger_id":3306,"name":"Error North Ramp","order":4,"passthrough":0},{"trigger_id":3393,"name":"Right Pillar Floor","order":5,"passthrough":0}]}