{
    "id": 10271,
    "map_id": 8,
    "name": "Ledge Grab Casual",
    "date": "2024-06-15T01:41:37.000Z",
    "author": "neposeda",
    "author_id": 10483,
    "last_updated": "2024-06-15T15:05:34.000Z",
    "last_updated_author_id": 457,
    "active": 1,
    "ranked": 1,
    "tier": 2,
    "points": 300,
    "max_prestrafe": 406,
    "completions": "15",
    "players_completed": "7",
    "average_rating": "0.0000",
    "sequence": [
        {
            "trigger_id": 1042,
            "name": "T2 Bottom Right Block",
            "order": 0,
            "passthrough": 0
        },
        {
            "trigger_id": 767,
            "name": "T2 Top Right Block",
            "order": 1,
            "passthrough": 0
        },
        {
            "trigger_id": 1042,
            "name": "T2 Bottom Right Block",
            "order": 2,
            "passthrough": 0
        },
        {
            "trigger_id": 1041,
            "name": "T2 Bottom Left Block",
            "order": 3,
            "passthrough": 0
        }
    ]
}