{
    "id": 2908,
    "map_id": 8,
    "name": "Holy Horizon",
    "date": "2022-05-05T18:00:00.000Z",
    "author": "bog",
    "author_id": 131,
    "last_updated": "2023-10-15T01:09:34.000Z",
    "last_updated_author_id": 457,
    "active": 1,
    "ranked": 1,
    "tier": 4,
    "points": 1000,
    "max_prestrafe": 406,
    "completions": "69",
    "players_completed": "35",
    "average_rating": "0.0000",
    "sequence": [
        {
            "trigger_id": 692,
            "name": "Jail Floor",
            "order": 0,
            "passthrough": 0
        },
        {
            "trigger_id": 709,
            "name": "Main Ramp",
            "order": 1,
            "passthrough": 0
        },
        {
            "trigger_id": 668,
            "name": "CT-Spawn Slant",
            "order": 2,
            "passthrough": 0
        },
        {
            "trigger_id": 683,
            "name": "Hamburger",
            "order": 3,
            "passthrough": 0
        }
    ]
}