{
    "id": 5654,
    "map_id": 8,
    "name": "p0no5",
    "date": "2022-06-11T14:40:14.000Z",
    "author": "Anti-Cheat | Autostrafing detect",
    "author_id": 416,
    "last_updated": "2023-10-13T17:17:16.000Z",
    "last_updated_author_id": 457,
    "active": 1,
    "ranked": 1,
    "tier": 6,
    "points": 2100,
    "max_prestrafe": 406,
    "completions": "5",
    "players_completed": "5",
    "average_rating": "0.0000",
    "sequence": [
        {
            "trigger_id": 705,
            "name": "Long Ramp Slant",
            "order": 0,
            "passthrough": 0
        },
        {
            "trigger_id": 698,
            "name": "Kevin Ramp",
            "order": 1,
            "passthrough": 0
        },
        {
            "trigger_id": 764,
            "name": "T2 Right Wing",
            "order": 2,
            "passthrough": 0
        },
        {
            "trigger_id": 728,
            "name": "Right Wing",
            "order": 3,
            "passthrough": 0
        },
        {
            "trigger_id": 709,
            "name": "Main Ramp",
            "order": 4,
            "passthrough": 0
        },
        {
            "trigger_id": 750,
            "name": "T-Spawn Slant",
            "order": 5,
            "passthrough": 0
        },
        {
            "trigger_id": 742,
            "name": "Spawn Roof Water",
            "order": 6,
            "passthrough": 0
        }
    ]
}