{
    "id": 10792,
    "map_id": 10,
    "name": "Boomer",
    "date": "2024-08-02T00:59:25.000Z",
    "last_updated": "2024-08-02T01:57:08.000Z",
    "author": "LuK ♛",
    "author_id": 18949,
    "last_updated_author_id": 18949,
    "active": 1,
    "points": 900,
    "tier": 5,
    "min_velocity": null,
    "max_prestrafe": 406,
    "max_duration": null,
    "max_jumps": 1,
    "no_jump": 1,
    "hidden": 0,
    "completions": 0,
    "playersCompleted": 0,
    "trick_sequence": [
        {
            "trigger_id": 1234,
            "order": 0,
            "passthrough": 0
        },
        {
            "trigger_id": 1764,
            "order": 1,
            "passthrough": 0
        },
        {
            "trigger_id": 2216,
            "order": 2,
            "passthrough": 0
        },
        {
            "trigger_id": 1231,
            "order": 3,
            "passthrough": 0
        },
        {
            "trigger_id": 1207,
            "order": 4,
            "passthrough": 0
        },
        {
            "trigger_id": 1588,
            "order": 5,
            "passthrough": 0
        },
        {
            "trigger_id": 1284,
            "order": 6,
            "passthrough": 0
        },
        {
            "trigger_id": 1286,
            "order": 7,
            "passthrough": 0
        },
        {
            "trigger_id": 1722,
            "order": 8,
            "passthrough": 0
        },
        {
            "trigger_id": 1431,
            "order": 9,
            "passthrough": 0
        },
        {
            "trigger_id": 1308,
            "order": 10,
            "passthrough": 0
        },
        {
            "trigger_id": 1746,
            "order": 11,
            "passthrough": 0
        },
        {
            "trigger_id": 1303,
            "order": 12,
            "passthrough": 0
        },
        {
            "trigger_id": 1303,
            "order": 13,
            "passthrough": 0
        },
        {
            "trigger_id": 1746,
            "order": 14,
            "passthrough": 0
        },
        {
            "trigger_id": 1308,
            "order": 15,
            "passthrough": 0
        },
        {
            "trigger_id": 1431,
            "order": 16,
            "passthrough": 0
        },
        {
            "trigger_id": 1406,
            "order": 17,
            "passthrough": 0
        },
        {
            "trigger_id": 1380,
            "order": 18,
            "passthrough": 0
        },
        {
            "trigger_id": 1305,
            "order": 19,
            "passthrough": 0
        }
    ]
}