{
    "id": 11349,
    "map_id": 10,
    "name": "Tenfold",
    "date": "2024-09-10T00:29:27.000Z",
    "author": "influx",
    "author_id": 147,
    "last_updated": null,
    "last_updated_author_id": 147,
    "active": 1,
    "ranked": 1,
    "tier": 4,
    "points": 1000,
    "max_prestrafe": 406,
    "completions": "0",
    "players_completed": "0",
    "average_rating": "0.0000",
    "sequence": [
        {
            "trigger_id": 1289,
            "name": "E Rooftops",
            "order": 0,
            "passthrough": 0
        },
        {
            "trigger_id": 1256,
            "name": "C Teal Ramp 6",
            "order": 1,
            "passthrough": 0
        },
        {
            "trigger_id": 1269,
            "name": "E Brown Ramp 5",
            "order": 2,
            "passthrough": 0
        },
        {
            "trigger_id": 1551,
            "name": "SE Black Ramp 4",
            "order": 3,
            "passthrough": 0
        },
        {
            "trigger_id": 1734,
            "name": "SE Large Pillar Gap West",
            "order": 4,
            "passthrough": 0
        },
        {
            "trigger_id": 2398,
            "name": "SE Large Pillar Gap South",
            "order": 5,
            "passthrough": 0
        },
        {
            "trigger_id": 1542,
            "name": "S Yellow Platform",
            "order": 6,
            "passthrough": 0
        }
    ]
}