{
    "id": 12836,
    "map_id": 10,
    "name": "Happy Feet",
    "date": "2025-05-19T11:29:55.000Z",
    "author": "hunter",
    "author_id": 4820,
    "last_updated": null,
    "last_updated_author_id": null,
    "active": 1,
    "ranked": 1,
    "tier": 7,
    "subtier": 3,
    "max_prestrafe": 261,
    "completions": "0",
    "players_completed": "0",
    "average_rating": "0.0000",
    "sequence": [
        {
            "trigger_id": 1724,
            "name": "SW Pink Pillar Booster 1",
            "order": 0,
            "passthrough": 0
        },
        {
            "trigger_id": 2177,
            "name": "SW Pink Pillar Slant 1",
            "order": 1,
            "passthrough": 0
        },
        {
            "trigger_id": 1558,
            "name": "SE Brown Ramp 1",
            "order": 2,
            "passthrough": 0
        },
        {
            "trigger_id": 2230,
            "name": "SE Under Brown Ramp 1",
            "order": 3,
            "passthrough": 0
        },
        {
            "trigger_id": 1545,
            "name": "S Yellow Ramp 9",
            "order": 4,
            "passthrough": 0
        },
        {
            "trigger_id": 1656,
            "name": "SW Yellow Ramp 7",
            "order": 5,
            "passthrough": 0
        },
        {
            "trigger_id": 1558,
            "name": "SE Brown Ramp 1",
            "order": 6,
            "passthrough": 0
        },
        {
            "trigger_id": 1595,
            "name": "SE Red Ramp 1",
            "order": 7,
            "passthrough": 0
        },
        {
            "trigger_id": 1560,
            "name": "SE Brown Ramp 2",
            "order": 8,
            "passthrough": 0
        },
        {
            "trigger_id": 1548,
            "name": "SE Spawn Roof East",
            "order": 9,
            "passthrough": 0
        }
    ]
}