{
    "id": 6898,
    "map_id": 10,
    "name": "Im Boss Ible",
    "date": "2023-01-29T20:31:59.000Z",
    "author": "Kassihici",
    "author_id": 3123,
    "last_updated": "2023-01-29T22:09:41.000Z",
    "last_updated_author_id": 347,
    "active": 1,
    "ranked": 1,
    "tier": 6,
    "subtier": 3,
    "max_prestrafe": 406,
    "completions": "0",
    "players_completed": "0",
    "average_rating": "0.0000",
    "sequence": [
        {
            "trigger_id": 1189,
            "name": "C Blue Platform",
            "order": 0,
            "passthrough": 0
        },
        {
            "trigger_id": 1190,
            "name": "C Blue Ramp 1",
            "order": 1,
            "passthrough": 0
        },
        {
            "trigger_id": 1443,
            "name": "NW Blue Ramp 2",
            "order": 2,
            "passthrough": 0
        },
        {
            "trigger_id": 1445,
            "name": "NW Blue Ramp 3",
            "order": 3,
            "passthrough": 0
        },
        {
            "trigger_id": 1190,
            "name": "C Blue Ramp 1",
            "order": 4,
            "passthrough": 0
        },
        {
            "trigger_id": 1486,
            "name": "NW Rooftops",
            "order": 5,
            "passthrough": 0
        }
    ]
}