{"id":9101,"map_id":10,"name":"Rammus","date":"2024-02-28T09:59:02.000Z","last_updated":"2024-02-28T17:39:04.000Z","author":"padu","author_id":15902,"last_updated_author_id":1137,"active":1,"points":1230,"tier":7,"min_velocity":null,"max_prestrafe":406,"max_duration":null,"max_jumps":1,"no_jump":0,"hidden":0,"completions":0,"playersCompleted":0,"trick_sequence":[{"trigger_id":1486,"order":0,"passthrough":0},{"trigger_id":1457,"order":1,"passthrough":0},{"trigger_id":1445,"order":2,"passthrough":0},{"trigger_id":2175,"order":3,"passthrough":0},{"trigger_id":1727,"order":4,"passthrough":0},{"trigger_id":1192,"order":5,"passthrough":0},{"trigger_id":1238,"order":6,"passthrough":0},{"trigger_id":1314,"order":7,"passthrough":0},{"trigger_id":1754,"order":8,"passthrough":0},{"trigger_id":1504,"order":9,"passthrough":0},{"trigger_id":1207,"order":10,"passthrough":0},{"trigger_id":1209,"order":11,"passthrough":0},{"trigger_id":1450,"order":12,"passthrough":0}]}