{
    "id": 5953,
    "map_id": 4,
    "name": "Real Kebab",
    "date": "2022-08-02T01:17:09.000Z",
    "author": "chief",
    "author_id": 75,
    "last_updated": "2022-08-02T01:19:47.000Z",
    "last_updated_author_id": 75,
    "active": 1,
    "ranked": 1,
    "tier": 6,
    "subtier": 1,
    "max_prestrafe": 406,
    "completions": "0",
    "players_completed": "0",
    "average_rating": "0.0000",
    "sequence": [
        {
            "trigger_id": 401,
            "name": "West Upper Ramp Top",
            "order": 0,
            "passthrough": 0
        },
        {
            "trigger_id": 346,
            "name": "Stage 6 Ramp",
            "order": 1,
            "passthrough": 0
        },
        {
            "trigger_id": 352,
            "name": "Lower Ramp Entry North",
            "order": 2,
            "passthrough": 0
        },
        {
            "trigger_id": 350,
            "name": "Lower Ramp",
            "order": 3,
            "passthrough": 0
        },
        {
            "trigger_id": 355,
            "name": "Middle Hole Grid",
            "order": 4,
            "passthrough": 0
        }
    ]
}