{"id":2558,"map_id":5,"name":"Back to Basics","date":"2022-01-31T12:00:00.000Z","author":"zSkyworld.com","author_id":null,"last_updated":null,"last_updated_author_id":null,"active":1,"ranked":1,"tier":3,"subtier":1,"max_prestrafe":406,"completions":"61","players_completed":"28","average_rating":"0.0000","sequence":[{"trigger_id":458,"name":"Spawn","order":0,"passthrough":0},{"trigger_id":434,"name":"Main Ramp","order":1,"passthrough":0},{"trigger_id":411,"name":"Blade Ramp","order":2,"passthrough":0},{"trigger_id":442,"name":"Pillar Medium","order":3,"passthrough":0},{"trigger_id":411,"name":"Blade Ramp","order":4,"passthrough":0},{"trigger_id":433,"name":"Main Ramp Slant","order":5,"passthrough":0},{"trigger_id":411,"name":"Blade Ramp","order":6,"passthrough":0},{"trigger_id":444,"name":"Pillar Small","order":7,"passthrough":0}]}