{"id":2564,"map_id":5,"name":"Hubby's Hard Adventure","date":"2022-01-31T12:00:00.000Z","author":"zSkyworld.com","author_id":null,"last_updated":null,"last_updated_author_id":null,"active":1,"ranked":1,"tier":4,"points":1000,"max_prestrafe":406,"completions":"21","players_completed":"16","average_rating":"0.0000","sequence":[{"trigger_id":422,"name":"Hub","order":0,"passthrough":0},{"trigger_id":461,"name":"Spine Ramp","order":1,"passthrough":0},{"trigger_id":478,"name":"Under Pool Tele","order":2,"passthrough":0},{"trigger_id":411,"name":"Blade Ramp","order":3,"passthrough":0},{"trigger_id":468,"name":"Through Pillar Medium","order":4,"passthrough":0},{"trigger_id":405,"name":"Back Ramp","order":5,"passthrough":0},{"trigger_id":411,"name":"Blade Ramp","order":6,"passthrough":0},{"trigger_id":433,"name":"Main Ramp Slant","order":7,"passthrough":0},{"trigger_id":411,"name":"Blade Ramp","order":8,"passthrough":0},{"trigger_id":440,"name":"Pillar Floor","order":9,"passthrough":0}]}