{
    "id": 2606,
    "map_id": 5,
    "name": "Advanced Curvy Business",
    "date": "2022-01-31T12:00:00.000Z",
    "author": "zSkyworld.com",
    "author_id": null,
    "last_updated": "2022-05-18T14:55:22.000Z",
    "last_updated_author_id": 209,
    "active": 1,
    "ranked": 1,
    "tier": 4,
    "points": 1000,
    "max_prestrafe": 406,
    "completions": "28",
    "players_completed": "13",
    "average_rating": "0.0000",
    "sequence": [
        {
            "trigger_id": 410,
            "name": "Below Spawn Platform",
            "order": 0,
            "passthrough": 0
        },
        {
            "trigger_id": 409,
            "name": "Below Spawn Boost",
            "order": 1,
            "passthrough": 0
        },
        {
            "trigger_id": 434,
            "name": "Main Ramp",
            "order": 2,
            "passthrough": 0
        },
        {
            "trigger_id": 482,
            "name": "Upper Curve Ramp",
            "order": 3,
            "passthrough": 0
        },
        {
            "trigger_id": 404,
            "name": "Awp Ramp",
            "order": 4,
            "passthrough": 0
        },
        {
            "trigger_id": 482,
            "name": "Upper Curve Ramp",
            "order": 5,
            "passthrough": 0
        },
        {
            "trigger_id": 440,
            "name": "Pillar Floor",
            "order": 6,
            "passthrough": 0
        }
    ]
}