{
    "id": 4883,
    "map_id": 7,
    "name": "Reverse Awp Around Main",
    "date": "2021-09-09T19:40:39.000Z",
    "author": "Fragzy4",
    "author_id": 1,
    "last_updated": null,
    "last_updated_author_id": null,
    "active": 1,
    "ranked": 1,
    "tier": 1,
    "subtier": 1,
    "max_prestrafe": null,
    "completions": "380",
    "players_completed": "75",
    "average_rating": "0.0000",
    "sequence": [
        {
            "trigger_id": 594,
            "name": "Awp Ramp",
            "order": 0,
            "passthrough": 0
        },
        {
            "trigger_id": 621,
            "name": "Over Main Ramp",
            "order": 1,
            "passthrough": 0
        },
        {
            "trigger_id": 602,
            "name": "Behind Main Ramp",
            "order": 2,
            "passthrough": 0
        },
        {
            "trigger_id": 594,
            "name": "Awp Ramp",
            "order": 3,
            "passthrough": 0
        }
    ]
}