{
    "id": 11078,
    "map_id": 13,
    "name": "Basic Rise",
    "date": "2024-08-26T23:56:50.000Z",
    "author": "Schewpid",
    "author_id": 25977,
    "last_updated": null,
    "last_updated_author_id": 147,
    "active": 1,
    "ranked": 1,
    "tier": 1,
    "subtier": 1,
    "max_prestrafe": 406,
    "completions": "4466",
    "players_completed": "215",
    "average_rating": "0.0000",
    "sequence": [
        {
            "trigger_id": 3413,
            "name": "Spawn Floor",
            "order": 0,
            "passthrough": 0
        },
        {
            "trigger_id": 3346,
            "name": "Main Ramp",
            "order": 1,
            "passthrough": 0
        },
        {
            "trigger_id": 3446,
            "name": "T2 High Corner",
            "order": 2,
            "passthrough": 0
        }
    ]
}