{"id":11142,"map_id":13,"name":"HNS Wet Dream","date":"2024-08-28T08:29:46.000Z","last_updated":"2024-08-31T17:14:56.000Z","author":"Autumn Melancholy","author_id":1159,"last_updated_author_id":1159,"active":1,"points":400,"tier":3,"min_velocity":null,"max_prestrafe":406,"max_duration":null,"max_jumps":null,"no_jump":0,"hidden":0,"completions":58,"playersCompleted":32,"trick_sequence":[{"trigger_id":3490,"order":0,"passthrough":0},{"trigger_id":3420,"order":1,"passthrough":0},{"trigger_id":3420,"order":2,"passthrough":0},{"trigger_id":3490,"order":3,"passthrough":0}]}