{
    "id": 2799,
    "map_id": 3,
    "name": "Jelly Flex",
    "date": "2021-09-05T13:35:30.000Z",
    "author": "adzicents",
    "author_id": 48,
    "last_updated": "2021-09-05T13:35:59.000Z",
    "last_updated_author_id": 48,
    "active": 1,
    "ranked": 1,
    "tier": 3,
    "subtier": 1,
    "max_prestrafe": 406,
    "completions": "39",
    "players_completed": "24",
    "average_rating": "0.0000",
    "sequence": [
        {
            "trigger_id": 235,
            "name": "Jail Top",
            "order": 0,
            "passthrough": 0
        },
        {
            "trigger_id": 231,
            "name": "Jail Ramp",
            "order": 1,
            "passthrough": 0
        },
        {
            "trigger_id": 230,
            "name": "Jail Pillar",
            "order": 2,
            "passthrough": 0
        }
    ]
}