{
    "id": 7102,
    "map_id": 3,
    "name": "Nostalgia's Nightmare",
    "date": "2023-02-21T06:05:08.000Z",
    "last_updated": "2023-02-21T06:07:03.000Z",
    "author": "nostalgia",
    "author_id": 4652,
    "last_updated_author_id": 480,
    "active": 1,
    "points": 550,
    "tier": 4,
    "min_velocity": null,
    "max_prestrafe": 406,
    "max_duration": null,
    "max_jumps": null,
    "no_jump": 0,
    "hidden": 0,
    "completions": 19,
    "playersCompleted": 12,
    "trick_sequence": [
        {
            "trigger_id": 223,
            "order": 0,
            "passthrough": 0
        },
        {
            "trigger_id": 241,
            "order": 1,
            "passthrough": 0
        },
        {
            "trigger_id": 233,
            "order": 2,
            "passthrough": 0
        }
    ]
}