{
    "id": 10157,
    "map_id": 8,
    "name": "Hangover",
    "date": "2024-06-11T16:31:47.000Z",
    "author": "shprot bossman",
    "author_id": 195,
    "last_updated": "2024-07-04T05:53:50.000Z",
    "last_updated_author_id": 2994,
    "active": 1,
    "ranked": 1,
    "tier": 5,
    "points": 1500,
    "max_prestrafe": 406,
    "completions": "0",
    "players_completed": "0",
    "average_rating": "0.0000",
    "sequence": [
        {
            "trigger_id": 109,
            "name": "Alpha UFO Roof",
            "order": 0,
            "passthrough": 0
        },
        {
            "trigger_id": 719,
            "name": "Mini Ramp",
            "order": 1,
            "passthrough": 0
        },
        {
            "trigger_id": 3222,
            "name": "T1 Middle Lower Ramp",
            "order": 2,
            "passthrough": 0
        },
        {
            "trigger_id": 657,
            "name": "Behind Spawn",
            "order": 3,
            "passthrough": 0
        },
        {
            "trigger_id": 748,
            "name": "T-Spawn Hole Back",
            "order": 4,
            "passthrough": 0
        },
        {
            "trigger_id": 749,
            "name": "T-Spawn Hole Front",
            "order": 5,
            "passthrough": 0
        },
        {
            "trigger_id": 709,
            "name": "Main Ramp",
            "order": 6,
            "passthrough": 0
        },
        {
            "trigger_id": 1058,
            "name": "Ring Ground",
            "order": 7,
            "passthrough": 0
        },
        {
            "trigger_id": 743,
            "name": "Sriracha",
            "order": 8,
            "passthrough": 0
        },
        {
            "trigger_id": 756,
            "name": "T1 Right Rail",
            "order": 9,
            "passthrough": 0
        }
    ]
}