{
    "id": 11005,
    "map_id": 2,
    "name": "Be home by 9",
    "date": "2024-08-20T14:13:05.000Z",
    "last_updated": null,
    "author": "Oscar",
    "author_id": 1554,
    "last_updated_author_id": 2994,
    "active": 1,
    "points": 3500,
    "tier": 8,
    "min_velocity": null,
    "max_prestrafe": 406,
    "max_duration": null,
    "max_jumps": 9,
    "no_jump": 0,
    "hidden": 0,
    "completions": 13,
    "playersCompleted": 4,
    "trick_sequence": [
        {
            "trigger_id": 155,
            "order": 0,
            "passthrough": 0
        },
        {
            "trigger_id": 143,
            "order": 1,
            "passthrough": 0
        },
        {
            "trigger_id": 128,
            "order": 2,
            "passthrough": 0
        },
        {
            "trigger_id": 136,
            "order": 3,
            "passthrough": 0
        },
        {
            "trigger_id": 136,
            "order": 4,
            "passthrough": 0
        },
        {
            "trigger_id": 128,
            "order": 5,
            "passthrough": 0
        },
        {
            "trigger_id": 143,
            "order": 6,
            "passthrough": 0
        },
        {
            "trigger_id": 121,
            "order": 7,
            "passthrough": 0
        },
        {
            "trigger_id": 970,
            "order": 8,
            "passthrough": 0
        },
        {
            "trigger_id": 154,
            "order": 9,
            "passthrough": 0
        },
        {
            "trigger_id": 143,
            "order": 10,
            "passthrough": 0
        },
        {
            "trigger_id": 128,
            "order": 11,
            "passthrough": 0
        },
        {
            "trigger_id": 136,
            "order": 12,
            "passthrough": 0
        },
        {
            "trigger_id": 136,
            "order": 13,
            "passthrough": 0
        },
        {
            "trigger_id": 128,
            "order": 14,
            "passthrough": 0
        },
        {
            "trigger_id": 143,
            "order": 15,
            "passthrough": 0
        },
        {
            "trigger_id": 121,
            "order": 16,
            "passthrough": 0
        },
        {
            "trigger_id": 155,
            "order": 17,
            "passthrough": 0
        }
    ]
}