{"id":6087,"map_id":2,"name":"The Pursuit of Excellence","date":"2022-09-20T00:10:23.000Z","last_updated":"2024-06-15T16:04:45.000Z","author":"KingYoshi // solidsurf.info","author_id":457,"last_updated_author_id":1,"active":1,"points":225,"tier":2,"min_velocity":null,"max_prestrafe":406,"max_duration":null,"max_jumps":null,"no_jump":0,"hidden":0,"completions":111,"playersCompleted":21,"trick_sequence":[{"trigger_id":187,"order":0,"passthrough":0},{"trigger_id":186,"order":1,"passthrough":0},{"trigger_id":145,"order":2,"passthrough":0},{"trigger_id":186,"order":3,"passthrough":0}]}