{
    "id": 2008,
    "map_id": 6,
    "name": "Survival V2",
    "date": "2022-03-03T18:00:00.000Z",
    "author": "zSkyworld.com",
    "author_id": null,
    "last_updated": "2022-03-04T15:41:29.000Z",
    "last_updated_author_id": 1,
    "active": 1,
    "ranked": 1,
    "tier": 2,
    "points": 300,
    "max_prestrafe": null,
    "completions": "0",
    "players_completed": "0",
    "average_rating": "0.0000",
    "sequence": [
        {
            "trigger_id": 501,
            "name": "Black & Yellow Ramp",
            "order": 0,
            "passthrough": 0
        },
        {
            "trigger_id": 506,
            "name": "Bottom Platform",
            "order": 1,
            "passthrough": 0
        }
    ]
}