{"id":10988,"map_id":12,"name":"i am one with the hops","date":"2024-08-19T05:42:52.000Z","author":"Steve","author_id":10,"last_updated":"2024-08-19T05:45:13.000Z","last_updated_author_id":10,"active":1,"ranked":1,"tier":5,"points":1500,"max_prestrafe":406,"completions":"1","players_completed":"1","average_rating":"0.0000","sequence":[{"trigger_id":2723,"name":"Right Back Pillar Beam","order":0,"passthrough":0},{"trigger_id":2536,"name":"Green-White Ramp","order":1,"passthrough":0},{"trigger_id":2531,"name":"Green Corner Block","order":2,"passthrough":0},{"trigger_id":2686,"name":"Purple-Green Ramp","order":3,"passthrough":0},{"trigger_id":2680,"name":"Purple Corner Block","order":4,"passthrough":0},{"trigger_id":2721,"name":"Red-Purple Ramp","order":5,"passthrough":0},{"trigger_id":2713,"name":"Red Corner Block","order":6,"passthrough":0},{"trigger_id":2948,"name":"White-Red Ramp","order":7,"passthrough":0},{"trigger_id":2586,"name":"Low Wall Fixture","order":8,"passthrough":0}]}