{
    "id": 10767,
    "map_id": 10,
    "name": "Jaquice",
    "date": "2024-07-29T08:46:29.000Z",
    "author": "Schewpid",
    "author_id": 25977,
    "last_updated": "2024-07-29T08:50:57.000Z",
    "last_updated_author_id": 4820,
    "active": 1,
    "ranked": 1,
    "tier": 2,
    "points": 300,
    "max_prestrafe": 406,
    "completions": "86",
    "players_completed": "21",
    "average_rating": "0.0000",
    "sequence": [
        {
            "trigger_id": 1601,
            "name": "SE Spawn Brown Platform",
            "order": 0,
            "passthrough": 0
        },
        {
            "trigger_id": 1558,
            "name": "SE Brown Ramp 1",
            "order": 1,
            "passthrough": 0
        },
        {
            "trigger_id": 1560,
            "name": "SE Brown Ramp 2",
            "order": 2,
            "passthrough": 0
        },
        {
            "trigger_id": 2396,
            "name": "S Under Yellow Ramp 8",
            "order": 3,
            "passthrough": 0
        },
        {
            "trigger_id": 1641,
            "name": "SW Purple Ramp 6",
            "order": 4,
            "passthrough": 0
        },
        {
            "trigger_id": 1610,
            "name": "SW Blue Ramp 5",
            "order": 5,
            "passthrough": 0
        },
        {
            "trigger_id": 1616,
            "name": "SW Corner Cubby",
            "order": 6,
            "passthrough": 0
        }
    ]
}