{"id":10868,"map_id":10,"name":"Eilat","date":"2024-08-10T20:14:20.000Z","author":"ASCENSION","author_id":10,"last_updated":"2024-08-10T20:15:28.000Z","last_updated_author_id":10,"active":1,"ranked":1,"tier":5,"subtier":1,"max_prestrafe":406,"completions":"21","players_completed":"12","average_rating":"0.0000","sequence":[{"trigger_id":1413,"name":"NE Lower Rooftops","order":0,"passthrough":0},{"trigger_id":1400,"name":"NE Green Ramp 4","order":1,"passthrough":0},{"trigger_id":1431,"name":"NE White Ramp 2","order":2,"passthrough":0},{"trigger_id":1308,"name":"E White Ramp 1","order":3,"passthrough":0},{"trigger_id":1303,"name":"E Through White Beams","order":4,"passthrough":0},{"trigger_id":1273,"name":"E High Platform","order":5,"passthrough":0}]}