{
    "id": 10924,
    "map_id": 10,
    "name": "Zenesis G90",
    "date": "2024-08-14T22:06:09.000Z",
    "author": "King",
    "author_id": 10,
    "last_updated": "2025-04-05T02:45:20.000Z",
    "last_updated_author_id": 4820,
    "active": 1,
    "ranked": 1,
    "tier": 7,
    "subtier": 3,
    "max_prestrafe": 406,
    "completions": "9",
    "players_completed": "7",
    "average_rating": "0.0000",
    "sequence": [
        {
            "trigger_id": 1273,
            "name": "E High Platform",
            "order": 0,
            "passthrough": 0
        },
        {
            "trigger_id": 1267,
            "name": "E Brown Ramp 4",
            "order": 1,
            "passthrough": 0
        },
        {
            "trigger_id": 1588,
            "name": "SE Orange Ramp 1",
            "order": 2,
            "passthrough": 0
        },
        {
            "trigger_id": 1597,
            "name": "SE Red Ramp 2",
            "order": 3,
            "passthrough": 0
        },
        {
            "trigger_id": 1775,
            "name": "SE Large Pillar Gap East",
            "order": 4,
            "passthrough": 0
        },
        {
            "trigger_id": 1304,
            "name": "E Upper Ground",
            "order": 5,
            "passthrough": 0
        }
    ]
}