{"id":11468,"map_id":10,"name":">_<","date":"2024-09-25T08:43:54.000Z","author":"Steve","author_id":10,"last_updated":"2024-09-25T08:45:37.000Z","last_updated_author_id":10,"active":1,"ranked":1,"tier":6,"points":2100,"max_prestrafe":406,"completions":"7","players_completed":"6","average_rating":"0.0000","sequence":[{"trigger_id":1593,"name":"SE East Pillar 4","order":0,"passthrough":0},{"trigger_id":1595,"name":"SE Red Ramp 1","order":1,"passthrough":0},{"trigger_id":1607,"name":"SE Structure Top","order":2,"passthrough":0},{"trigger_id":1552,"name":"SE Black Ramp 4 Spine","order":3,"passthrough":0},{"trigger_id":1531,"name":"S Fort Floor","order":4,"passthrough":0},{"trigger_id":1670,"name":"W Orange Ramp 5","order":5,"passthrough":0},{"trigger_id":1208,"name":"C Orange Ramp 2 Spine","order":6,"passthrough":0}]}