{"id":5913,"map_id":10,"name":"Maybach","date":"2022-10-28T18:00:00.000Z","author":"Ghostface","author_id":5,"last_updated":"2023-03-08T22:01:27.000Z","last_updated_author_id":5,"active":1,"ranked":1,"tier":5,"points":1500,"max_prestrafe":406,"completions":"305","players_completed":"73","average_rating":"0.0000","sequence":[{"trigger_id":1513,"name":"NW Yellow Platform","order":0,"passthrough":0},{"trigger_id":1514,"name":"NW Yellow Ramp 1","order":1,"passthrough":0},{"trigger_id":1516,"name":"NW Yellow Ramp 2","order":2,"passthrough":0},{"trigger_id":1660,"name":"W Blue Ramp 4","order":3,"passthrough":0},{"trigger_id":1610,"name":"SW Blue Ramp 5","order":4,"passthrough":0},{"trigger_id":1212,"name":"C Orange Ramp 4","order":5,"passthrough":0},{"trigger_id":1264,"name":"E Brown Beam 1","order":6,"passthrough":0}]}