{
    "id": 6271,
    "map_id": 10,
    "name": "Dina's concrete adventure",
    "date": "2022-10-31T18:53:55.000Z",
    "last_updated": "2022-12-14T22:15:38.000Z",
    "author": "oski   .͜.",
    "author_id": 194,
    "last_updated_author_id": 347,
    "active": 1,
    "points": 375,
    "tier": 3,
    "min_velocity": null,
    "max_prestrafe": 406,
    "max_duration": null,
    "max_jumps": null,
    "no_jump": 0,
    "hidden": 0,
    "completions": 84,
    "playersCompleted": 32,
    "trick_sequence": [
        {
            "trigger_id": 1279,
            "order": 0,
            "passthrough": 0
        },
        {
            "trigger_id": 1278,
            "order": 1,
            "passthrough": 0
        },
        {
            "trigger_id": 1545,
            "order": 2,
            "passthrough": 0
        },
        {
            "trigger_id": 1551,
            "order": 3,
            "passthrough": 0
        },
        {
            "trigger_id": 1207,
            "order": 4,
            "passthrough": 0
        },
        {
            "trigger_id": 1209,
            "order": 5,
            "passthrough": 0
        },
        {
            "trigger_id": 1199,
            "order": 6,
            "passthrough": 0
        },
        {
            "trigger_id": 1194,
            "order": 7,
            "passthrough": 0
        },
        {
            "trigger_id": 1276,
            "order": 8,
            "passthrough": 0
        },
        {
            "trigger_id": 1279,
            "order": 9,
            "passthrough": 0
        }
    ]
}