{"id":6587,"map_id":10,"name":"Elevator King","date":"2022-12-23T23:10:44.000Z","last_updated":"2022-12-23T23:35:56.000Z","author":"KingYoshi","author_id":457,"last_updated_author_id":457,"active":1,"points":1225,"tier":7,"min_velocity":null,"max_prestrafe":406,"max_duration":null,"max_jumps":null,"no_jump":0,"hidden":0,"completions":16,"playersCompleted":13,"trick_sequence":[{"trigger_id":1373,"order":0,"passthrough":0},{"trigger_id":1344,"order":1,"passthrough":0},{"trigger_id":1345,"order":2,"passthrough":0},{"trigger_id":1512,"order":3,"passthrough":0}]}