{"id":7279,"map_id":10,"name":"Aqua Iulia","date":"2023-03-04T04:36:24.000Z","author":"Daxen","author_id":1642,"last_updated":"2023-03-04T20:44:16.000Z","last_updated_author_id":74,"active":1,"ranked":1,"tier":4,"subtier":1,"max_prestrafe":406,"completions":"11","players_completed":"10","average_rating":"0.0000","sequence":[{"trigger_id":1582,"name":"SE High Pillar Top","order":0,"passthrough":0},{"trigger_id":1558,"name":"SE Brown Ramp 1","order":1,"passthrough":0},{"trigger_id":1267,"name":"E Brown Ramp 4","order":2,"passthrough":0},{"trigger_id":1192,"name":"C Blue Ramp 6","order":3,"passthrough":0},{"trigger_id":1727,"name":"C Undergrounds Entry West","order":4,"passthrough":0},{"trigger_id":1670,"name":"W Orange Ramp 5","order":5,"passthrough":0},{"trigger_id":1640,"name":"SW Purple Platform","order":6,"passthrough":0},{"trigger_id":1761,"name":"SW Purple Teleporter","order":7,"passthrough":0},{"trigger_id":1256,"name":"C Teal Ramp 6","order":8,"passthrough":0},{"trigger_id":1313,"name":"N Archway Top","order":9,"passthrough":0}]}