{
    "id": 8984,
    "map_id": 10,
    "name": "Mortar",
    "date": "2024-02-16T05:40:18.000Z",
    "last_updated": "2024-05-18T08:22:32.000Z",
    "author": "inf",
    "author_id": 147,
    "last_updated_author_id": 147,
    "active": 1,
    "points": 400,
    "tier": 3,
    "min_velocity": null,
    "max_prestrafe": 406,
    "max_duration": null,
    "max_jumps": 2,
    "no_jump": 0,
    "hidden": 0,
    "completions": 18,
    "playersCompleted": 12,
    "trick_sequence": [
        {
            "trigger_id": 1590,
            "order": 0,
            "passthrough": 0
        },
        {
            "trigger_id": 1311,
            "order": 1,
            "passthrough": 0
        },
        {
            "trigger_id": 1284,
            "order": 2,
            "passthrough": 0
        },
        {
            "trigger_id": 1308,
            "order": 3,
            "passthrough": 0
        },
        {
            "trigger_id": 1263,
            "order": 4,
            "passthrough": 0
        },
        {
            "trigger_id": 1269,
            "order": 5,
            "passthrough": 0
        },
        {
            "trigger_id": 1267,
            "order": 6,
            "passthrough": 0
        },
        {
            "trigger_id": 2211,
            "order": 7,
            "passthrough": 0
        },
        {
            "trigger_id": 2209,
            "order": 8,
            "passthrough": 0
        },
        {
            "trigger_id": 1274,
            "order": 9,
            "passthrough": 0
        },
        {
            "trigger_id": 1504,
            "order": 10,
            "passthrough": 0
        },
        {
            "trigger_id": 1551,
            "order": 11,
            "passthrough": 0
        },
        {
            "trigger_id": 1733,
            "order": 12,
            "passthrough": 0
        },
        {
            "trigger_id": 1583,
            "order": 13,
            "passthrough": 0
        },
        {
            "trigger_id": 1775,
            "order": 14,
            "passthrough": 0
        },
        {
            "trigger_id": 1597,
            "order": 15,
            "passthrough": 0
        },
        {
            "trigger_id": 1733,
            "order": 16,
            "passthrough": 0
        },
        {
            "trigger_id": 1532,
            "order": 17,
            "passthrough": 0
        }
    ]
}