{"id":9052,"map_id":10,"name":"Droptop","date":"2024-02-23T08:22:33.000Z","author":"Steve","author_id":10,"last_updated":"2024-07-28T02:35:55.000Z","last_updated_author_id":10,"active":1,"ranked":1,"tier":7,"points":2800,"max_prestrafe":406,"completions":"71","players_completed":"36","average_rating":"0.0000","sequence":[{"trigger_id":1599,"name":"SE Rooftops","order":0,"passthrough":0},{"trigger_id":1600,"name":"SE Rooftops Booster","order":1,"passthrough":0},{"trigger_id":1561,"name":"SE Brown Ramp 2 Spine","order":2,"passthrough":0},{"trigger_id":1562,"name":"SE Brown Ramp 3","order":3,"passthrough":0},{"trigger_id":1550,"name":"SE Black Platform","order":4,"passthrough":0}]}