{
    "id": 9272,
    "map_id": 10,
    "name": "Kai",
    "date": "2024-03-13T21:37:41.000Z",
    "last_updated": "2024-03-13T21:46:18.000Z",
    "author": "kza",
    "author_id": 9110,
    "last_updated_author_id": 1137,
    "active": 1,
    "points": 550,
    "tier": 4,
    "min_velocity": null,
    "max_prestrafe": 406,
    "max_duration": null,
    "max_jumps": 1,
    "no_jump": 1,
    "hidden": 0,
    "completions": 13,
    "playersCompleted": 10,
    "trick_sequence": [
        {
            "trigger_id": 1462,
            "order": 0,
            "passthrough": 0
        },
        {
            "trigger_id": 1463,
            "order": 1,
            "passthrough": 0
        },
        {
            "trigger_id": 1447,
            "order": 2,
            "passthrough": 0
        },
        {
            "trigger_id": 1660,
            "order": 3,
            "passthrough": 0
        },
        {
            "trigger_id": 1670,
            "order": 4,
            "passthrough": 0
        },
        {
            "trigger_id": 1443,
            "order": 5,
            "passthrough": 0
        },
        {
            "trigger_id": 1384,
            "order": 6,
            "passthrough": 0
        },
        {
            "trigger_id": 1347,
            "order": 7,
            "passthrough": 0
        },
        {
            "trigger_id": 1387,
            "order": 8,
            "passthrough": 0
        },
        {
            "trigger_id": 1431,
            "order": 9,
            "passthrough": 0
        },
        {
            "trigger_id": 1431,
            "order": 10,
            "passthrough": 0
        },
        {
            "trigger_id": 1430,
            "order": 11,
            "passthrough": 0
        }
    ]
}