{
    "id": 9356,
    "map_id": 10,
    "name": "mc john boi track 3 b2b mc triken",
    "date": "2024-03-22T01:48:29.000Z",
    "author": "ttv/bzukey",
    "author_id": 18529,
    "last_updated": "2024-11-01T05:47:06.000Z",
    "last_updated_author_id": 18519,
    "active": 1,
    "ranked": 1,
    "tier": 6,
    "points": 2100,
    "max_prestrafe": 406,
    "completions": "9",
    "players_completed": "5",
    "average_rating": "0.0000",
    "sequence": [
        {
            "trigger_id": 1307,
            "name": "E White Platform",
            "order": 0,
            "passthrough": 0
        },
        {
            "trigger_id": 1308,
            "name": "E White Ramp 1",
            "order": 1,
            "passthrough": 0
        },
        {
            "trigger_id": 1731,
            "name": "E Under White Beams",
            "order": 2,
            "passthrough": 0
        },
        {
            "trigger_id": 1267,
            "name": "E Brown Ramp 4",
            "order": 3,
            "passthrough": 0
        },
        {
            "trigger_id": 2211,
            "name": "E Under High Platform",
            "order": 4,
            "passthrough": 0
        },
        {
            "trigger_id": 1588,
            "name": "SE Orange Ramp 1",
            "order": 5,
            "passthrough": 0
        },
        {
            "trigger_id": 1551,
            "name": "SE Black Ramp 4",
            "order": 6,
            "passthrough": 0
        },
        {
            "trigger_id": 2397,
            "name": "S Under Yellow Ramp 9",
            "order": 7,
            "passthrough": 0
        },
        {
            "trigger_id": 2396,
            "name": "S Under Yellow Ramp 8",
            "order": 8,
            "passthrough": 0
        },
        {
            "trigger_id": 1641,
            "name": "SW Purple Ramp 6",
            "order": 9,
            "passthrough": 0
        },
        {
            "trigger_id": 1656,
            "name": "SW Yellow Ramp 7",
            "order": 10,
            "passthrough": 0
        },
        {
            "trigger_id": 1654,
            "name": "SW Yellow Ramp 6",
            "order": 11,
            "passthrough": 0
        },
        {
            "trigger_id": 1660,
            "name": "W Blue Ramp 4",
            "order": 12,
            "passthrough": 0
        },
        {
            "trigger_id": 1727,
            "name": "C Undergrounds Entry West",
            "order": 13,
            "passthrough": 0
        },
        {
            "trigger_id": 1259,
            "name": "C Undergrounds",
            "order": 14,
            "passthrough": 0
        }
    ]
}