{
    "id": 9955,
    "map_id": 10,
    "name": "Lychee Ice",
    "date": "2024-05-16T00:54:31.000Z",
    "author": "nex",
    "author_id": 18519,
    "last_updated": "2024-05-16T04:43:40.000Z",
    "last_updated_author_id": 18519,
    "active": 1,
    "ranked": 1,
    "tier": 5,
    "points": 1500,
    "max_prestrafe": 406,
    "completions": "43",
    "players_completed": "11",
    "average_rating": "0.0000",
    "sequence": [
        {
            "trigger_id": 1392,
            "name": "NE Building Top",
            "order": 0,
            "passthrough": 0
        },
        {
            "trigger_id": 1400,
            "name": "NE Green Ramp 4",
            "order": 1,
            "passthrough": 0
        },
        {
            "trigger_id": 1431,
            "name": "NE White Ramp 2",
            "order": 2,
            "passthrough": 0
        },
        {
            "trigger_id": 1308,
            "name": "E White Ramp 1",
            "order": 3,
            "passthrough": 0
        },
        {
            "trigger_id": 1303,
            "name": "E Through White Beams",
            "order": 4,
            "passthrough": 0
        },
        {
            "trigger_id": 1637,
            "name": "E Large Pillar Gap West 2",
            "order": 5,
            "passthrough": 0
        },
        {
            "trigger_id": 1205,
            "name": "C Lift Platform",
            "order": 6,
            "passthrough": 0
        }
    ]
}