{
    "id": 7108,
    "map_id": 9,
    "name": "epic winter's rise",
    "date": "2023-02-24T18:00:00.000Z",
    "last_updated": "2023-03-04T20:14:15.000Z",
    "author": "winter",
    "author_id": 406,
    "last_updated_author_id": 406,
    "active": 1,
    "points": 1225,
    "tier": 7,
    "min_velocity": null,
    "max_prestrafe": 406,
    "max_duration": null,
    "max_jumps": null,
    "no_jump": 0,
    "hidden": 0,
    "completions": 20,
    "playersCompleted": 14,
    "trick_sequence": [
        {
            "trigger_id": 823,
            "order": 0,
            "passthrough": 0
        },
        {
            "trigger_id": 800,
            "order": 1,
            "passthrough": 0
        },
        {
            "trigger_id": 799,
            "order": 2,
            "passthrough": 0
        },
        {
            "trigger_id": 817,
            "order": 3,
            "passthrough": 0
        }
    ]
}