{"id":8791,"map_id":12,"name":"Hoppin about","date":"2024-01-14T06:10:43.000Z","last_updated":null,"author":"ᴛꜱ ٠ King","author_id":10,"last_updated_author_id":10,"active":1,"points":300,"tier":3,"min_velocity":null,"max_prestrafe":406,"max_duration":null,"max_jumps":4,"no_jump":0,"hidden":0,"completions":0,"playersCompleted":0,"trick_sequence":[{"trigger_id":2858,"order":0,"passthrough":0},{"trigger_id":2856,"order":1,"passthrough":0},{"trigger_id":2590,"order":2,"passthrough":0},{"trigger_id":3106,"order":3,"passthrough":0},{"trigger_id":2591,"order":4,"passthrough":0},{"trigger_id":3136,"order":5,"passthrough":0},{"trigger_id":2796,"order":6,"passthrough":0}]}