{
    "id": 6144,
    "map_id": 11,
    "name": "Easy-U",
    "date": "2023-04-14T18:00:00.000Z",
    "author": "IrynStyl",
    "author_id": 2076,
    "last_updated": "2023-05-19T22:20:49.000Z",
    "last_updated_author_id": 103,
    "active": 1,
    "ranked": 1,
    "tier": 1,
    "subtier": 1,
    "max_prestrafe": 406,
    "completions": "256",
    "players_completed": "77",
    "average_rating": "0.0000",
    "sequence": [
        {
            "trigger_id": 1895,
            "name": "Main Platform",
            "order": 0,
            "passthrough": 0
        },
        {
            "trigger_id": 1898,
            "name": "Main Ramp",
            "order": 1,
            "passthrough": 0
        },
        {
            "trigger_id": 1937,
            "name": "Poorly Rotated Ramp",
            "order": 2,
            "passthrough": 0
        },
        {
            "trigger_id": 1859,
            "name": "Half Pipe Right Ramp",
            "order": 3,
            "passthrough": 0
        },
        {
            "trigger_id": 2155,
            "name": "U Top Hole",
            "order": 4,
            "passthrough": 0
        },
        {
            "trigger_id": 2151,
            "name": "U Curvy Boi",
            "order": 5,
            "passthrough": 0
        },
        {
            "trigger_id": 1876,
            "name": "U Trigger",
            "order": 6,
            "passthrough": 0
        }
    ]
}