{"id":5416,"map_id":6,"name":"KingYoshi's Deathwish","date":"2022-05-01T08:20:30.000Z","author":"LarzZz^","author_id":181,"last_updated":"2022-05-04T16:07:15.000Z","last_updated_author_id":174,"active":1,"ranked":1,"tier":7,"subtier":1,"max_prestrafe":406,"completions":"5","players_completed":"5","average_rating":"0.0000","sequence":[{"trigger_id":528,"name":"Large Sniper Disk","order":0,"passthrough":0},{"trigger_id":525,"name":"Jail Ramp","order":1,"passthrough":0},{"trigger_id":571,"name":"Through Wheel 1","order":2,"passthrough":0},{"trigger_id":525,"name":"Jail Ramp","order":3,"passthrough":0},{"trigger_id":544,"name":"Red Ramp","order":4,"passthrough":0},{"trigger_id":589,"name":"Right Glass Ramp Platform","order":5,"passthrough":0}]}